<?xml version="1.0" encoding="utf-8" ?><dwsync><file name="tcp-en_GB.mo" server="grandmassoup.org" local="3423597900" remote="20603467084" /><file name="tcp-en_GB.po" server="grandmassoup.org" local="3423597900" remote="20603467084" /><file name="tcp-en_US.mo" server="grandmassoup.org" local="3423597900" remote="20603467084" /><file name="tcp-en_US.po" server="grandmassoup.org" local="3423597900" remote="20603467084" /><file name="tcp-fr_FR.mo" server="grandmassoup.org" local="3423597900" remote="20603467084" /><file name="tcp-fr_FR.po" server="grandmassoup.org" local="3423597900" remote="20603467084" /><file name="tcp-hu_HU.mo" server="grandmassoup.org" local="3423597900" remote="20603467084" /><file name="tcp-hu_HU.po" server="grandmassoup.org" local="3423597900" remote="20603467084" /><file name="tcp-it_IT.mo" server="grandmassoup.org" local="3423597900" remote="20603467084" /><file name="tcp-it_IT.po" server="grandmassoup.org" local="3423597900" remote="20603467084" /><file name="tcp-pl_PL.mo" server="grandmassoup.org" local="3423597900" remote="20603467084" /><file name="tcp-pl_PL.po" server="grandmassoup.org" local="3423597900" remote="20603467084" /><file name="tcp-pt_PT.mo" server="grandmassoup.org" local="3423597900" remote="20603467084" /><file name="tcp-pt_PT.po" server="grandmassoup.org" local="3423597900" remote="20603467084" /><file name="tcp-sv_SE.mo" server="grandmassoup.org" local="3423597900" remote="20603467084" /><file name="tcp-sv_SE.po" server="grandmassoup.org" local="3423597900" remote="20603467084" /><file name="tcp-ua.mo" server="grandmassoup.org" local="3423597900" remote="20603467084" /><file name="tcp-ua.po" server="grandmassoup.org" local="3423597900" remote="20603467084" /><file name="tcp-uk.mo" server="grandmassoup.org" local="3423597900" remote="20603467084" /><file name="tcp-uk.po" server="grandmassoup.org" local="3423597900" remote="20603467084" /><file name="tcp.mo" server="grandmassoup.org" local="3423597900" remote="20603467084" /><file name="tcp.po" server="grandmassoup.org" local="3423597900" remote="20603467084" /></dwsync>